opendota/__init__.py
opendota/cli.py
opendota/opendota.py
pyopendota-0.2.9.dist-info/AUTHORS.rst
pyopendota-0.2.9.dist-info/LICENSE
pyopendota-0.2.9.dist-info/METADATA
pyopendota-0.2.9.dist-info/WHEEL
pyopendota-0.2.9.dist-info/entry_points.txt
pyopendota-0.2.9.dist-info/top_level.txt
pyopendota-0.2.9.dist-info/RECORD
