Metadata-Version: 2.1
Name: pyopendota
Version: 0.2.9
Summary: A python interface for <OPENDOTA/> API
Home-page: https://github.com/hrishikeshrt/pyopendota
Author: Hrishikesh Terdalkar
Author-email: hrishikeshrt@linuxmail.org
License: MIT license
Keywords: opendota
Classifier: Development Status :: 2 - Pre-Alpha
Classifier: Intended Audience :: Developers
Classifier: License :: OSI Approved :: MIT License
Classifier: Natural Language :: English
Classifier: Programming Language :: Python :: 3
Classifier: Programming Language :: Python :: 3.6
Classifier: Programming Language :: Python :: 3.7
Classifier: Programming Language :: Python :: 3.8
Classifier: Programming Language :: Python :: 3.9
Classifier: Programming Language :: Python :: 3.10
Classifier: Topic :: Games/Entertainment
Classifier: Topic :: Games/Entertainment :: Real Time Strategy
Requires-Python: >=3.6
License-File: LICENSE
License-File: AUTHORS.rst
